{
    "animals": [
    {
        "animal": "Alpaca",
        "gurmukhi": "ਅਲਪਾਕਾ",
        "image": "https://example.com/images/alpaca.jpg"
    },
    {
        "animal": "Alligator",
        "gurmukhi": "ਐਲੀਗੇਟਰ",
        "image": "https://example.com/images/alligator.jpg"
    },
    {
        "animal": "Ant",
        "gurmukhi": "ਐਂਟ",
        "image": "https://example.com/images/ant.jpg"
    },
    {
        "animal": "Antelope",
        "gurmukhi": "ਐਂਟੀਲੋਪ",
        "image": "https://example.com/images/antelope.jpg"
    },
    {
        "animal": "Armadillo",
        "gurmukhi": "ਆਰਮਾਡਿਲੋ",
        "image": "https://example.com/images/armadillo.jpg"
    },
    {
        "animal": "Bat",
        "gurmukhi": "ਬੈਟ",
        "image": "https://example.com/images/bat.jpg"
    },
    {
        "animal": "Bear",
        "gurmukhi": "ਬੇਅਰ",
        "image": "https://example.com/images/bear.jpg"
    },
    {
        "animal": "Bee",
        "gurmukhi": "ਬੀ",
        "image": "https://example.com/images/bee.jpg"
    },
    {
        "animal": "Bison",
        "gurmukhi": "ਬਾਈਸਨ",
        "image": "https://example.com/images/bison.jpg"
    },
    {
        "animal": "Buffalo",
        "gurmukhi": "ਬਫੈਲੋ",
        "image": "https://example.com/images/buffalo.jpg"
    },
    {
        "animal": "Butterfly",
        "gurmukhi": "ਬਟਰਫਲਾਈ",
        "image": "https://example.com/images/butterfly.jpg"
    },
    {
        "animal": "Camel",
        "gurmukhi": "ਕੈਮਲ",
        "image": "https://example.com/images/camel.jpg"
    },
    {
        "animal": "Caribou",
        "gurmukhi": "ਕੈਰੀਬੂ",
        "image": "https://example.com/images/caribou.jpg"
    },
    {
        "animal": "Cat",
        "gurmukhi": "ਕੈਟ",
        "image": "https://example.com/images/cat.jpg"
    },
    {
        "animal": "Cheetah",
        "gurmukhi": "ਚੀਟਾਹ",
        "image": "https://example.com/images/cheetah.jpg"
    },
    {
        "animal": "Chicken",
        "gurmukhi": "ਚਿਕਨ",
        "image": "https://example.com/images/chicken.jpg"
    },
    {
        "animal": "Chameleon",
        "gurmukhi": "ਕੈਮਿਲੀਅਨ",
        "image": "https://example.com/images/chameleon.jpg"
    },
    {
        "animal": "Condor",
        "gurmukhi": "ਕੌਂਡਰ",
        "image": "https://example.com/images/condor.jpg"
    },
    {
        "animal": "Cormorant",
        "gurmukhi": "ਕੌਰਮੋਰੈਂਟ",
        "image": "https://example.com/images/cormorant.jpg"
    },
    {
        "animal": "Cow",
        "gurmukhi": "ਕਾਉ",
        "image": "https://example.com/images/cow.jpg"
    },
    {
        "animal": "Crab",
        "gurmukhi": "ਕ੍ਰੈਬ",
        "image": "https://example.com/images/crab.jpg"
    },
    {
        "animal": "Crane",
        "gurmukhi": "ਕਰੇਨ",
        "image": "https://example.com/images/crane.jpg"
    },
    {
        "animal": "Crocodile",
        "gurmukhi": "ਕਰੋਕੋਡਾਇਲ",
        "image": "https://example.com/images/crocodile.jpg"
    },
    {
        "animal": "Crow",
        "gurmukhi": "ਕਰੋ",
        "image": "https://example.com/images/crow.jpg"
    },
    {
        "animal": "Deer",
        "gurmukhi": "ਡੀਅਰ",
        "image": "https://example.com/images/deer.jpg"
    },
    {
        "animal": "Dog",
        "gurmukhi": "ਡਾਗ",
        "image": "https://example.com/images/dog.jpg"
    },
    {
        "animal": "Dolphin",
        "gurmukhi": "ਡਾਲਫਿਨ",
        "image": "https://example.com/images/dolphin.jpg"
    },
    {
        "animal": "Donkey",
        "gurmukhi": "ਡਾਂਕੀ",
        "image": "https://example.com/images/donkey.jpg"
    },
    {
        "animal": "Duck",
        "gurmukhi": "ਡਕ",
        "image": "https://example.com/images/duck.jpg"
    },
    {
        "animal": "Eagle",
        "gurmukhi": "ਈਗਲ",
        "image": "https://example.com/images/eagle.jpg"
    },
    {
        "animal": "Elephant",
        "gurmukhi": "ਐਲੀਫੈਂਟ",
        "image": "https://example.com/images/elephant.jpg"
    },
    {
        "animal": "Emu",
        "gurmukhi": "ਈਮੂ",
        "image": "https://example.com/images/emu.jpg"
    },
    {
        "animal": "Falcon",
        "gurmukhi": "ਫਾਲਕਨ",
        "image": "https://example.com/images/falcon.jpg"
    },
    {
        "animal": "Fish",
        "gurmukhi": "ਫਿਸ਼",
        "image": "https://example.com/images/fish.jpg"
    },
    {
        "animal": "Flamingo",
        "gurmukhi": "ਫਲੇਮਿੰਗੋ",
        "image": "https://example.com/images/flamingo.jpg"
    },
    {
        "animal": "Fox",
        "gurmukhi": "ਫਾਕਸ",
        "image": "https://example.com/images/fox.jpg"
    },
    {
        "animal": "Frog",
        "gurmukhi": "ਫਰਾਗ",
        "image": "https://example.com/images/frog.jpg"
    },
    {
        "animal": "Gazelle",
        "gurmukhi": "ਗਜ਼ੇਲ",
        "image": "https://example.com/images/gazelle.jpg"
    },
    {
        "animal": "Giraffe",
        "gurmukhi": "ਜਿਰਾਫ",
        "image": "https://example.com/images/giraffe.jpg"
    },
    {
        "animal": "Goat",
        "gurmukhi": "ਗੋਟ",
        "image": "https://example.com/images/goat.jpg"
    },
    {
        "animal": "Hawk",
        "gurmukhi": "ਹਾਕ",
        "image": "https://example.com/images/hawk.jpg"
    },
    {
        "animal": "Hedgehog",
        "gurmukhi": "ਹੇਜਹਾਗ",
        "image": "https://example.com/images/hedgehog.jpg"
    },
    {
        "animal": "Heron",
        "gurmukhi": "ਹੇਰੋਨ",
        "image": "https://example.com/images/heron.jpg"
    },
    {
        "animal": "Hippopotamus",
        "gurmukhi": "ਹਿਪੋਪੋਟਾਮਸ",
        "image": "https://example.com/images/hippopotamus.jpg"
    },
    {
        "animal": "Horse",
        "gurmukhi": "ਹੋਰਸ",
        "image": "https://example.com/images/horse.jpg"
    },
    {
        "animal": "Hyena",
        "gurmukhi": "ਹਾਈਨਾ",
        "image": "https://example.com/images/hyena.jpg"
    },
    {
        "animal": "Jellyfish",
        "gurmukhi": "ਜੈਲੀਫਿਸ਼",
        "image": "https://example.com/images/jellyfish.jpg"
    },
    {
        "animal": "Kangaroo",
        "gurmukhi": "ਕੈਂਗਰੂ",
        "image": "https://example.com/images/kangaroo.jpg"
    },
    {
        "animal": "Kiwi",
        "gurmukhi": "ਕੀਵੀ",
        "image": "https://example.com/images/kiwi.jpg"
    },
    {
        "animal": "Koala",
        "gurmukhi": "ਕੋਆਲਾ",
        "image": "https://example.com/images/koala.jpg"
    },
    {
        "animal": "Leopard",
        "gurmukhi": "ਲੇਪਾਰਡ",
        "image": "https://example.com/images/leopard.jpg"
    },
    {
        "animal": "Lion",
        "gurmukhi": "ਲਾਇਅਨ",
        "image": "https://example.com/images/lion.jpg"
    },
    {
        "animal": "Llama",
        "gurmukhi": "ਲਾਮਾ",
        "image": "https://example.com/images/llama.jpg"
    },
    {
        "animal": "Lobster",
        "gurmukhi": "ਲਾਬਸਟਰ",
        "image": "https://example.com/images/lobster.jpg"
    },
    {
        "animal": "Meerkat",
        "gurmukhi": "ਮੀਰਕੈਟ",
        "image": "https://example.com/images/meerkat.jpg"
    },
    {
        "animal": "Mole",
        "gurmukhi": "ਮੋਲ",
        "image": "https://example.com/images/mole.jpg"
    },
    {
        "animal": "Monkey",
        "gurmukhi": "ਮੰਕੀ",
        "image": "https://example.com/images/monkey.jpg"
    },
    {
        "animal": "Moose",
        "gurmukhi": "ਮੂਸ",
        "image": "https://example.com/images/moose.jpg"
    },
    {
        "animal": "Octopus",
        "gurmukhi": "ਆਕਟੋਪਸ",
        "image": "https://example.com/images/octopus.jpg"
    },
    {
        "animal": "Ostrich",
        "gurmukhi": "ਆਸਟ੍ਰਿਚ",
        "image": "https://example.com/images/ostrich.jpg"
    },
    {
        "animal": "Otter",
        "gurmukhi": "ਆਟਰ",
        "image": "https://example.com/images/otter.jpg"
    },
    {
        "animal": "Owl",
        "gurmukhi": "ਆਊਲ",
        "image": "https://example.com/images/owl.jpg"
    },
    {
        "animal": "Panda",
        "gurmukhi": "ਪਾਂਡਾ",
        "image": "https://example.com/images/panda.jpg"
    },
    {
        "animal": "Parrot",
        "gurmukhi": "ਪੈਰਟ",
        "image": "https://example.com/images/parrot.jpg"
    },
    {
        "animal": "Peacock",
        "gurmukhi": "ਪੀਕਾਕ",
        "image": "https://example.com/images/peacock.jpg"
    },
    {
        "animal": "Pelican",
        "gurmukhi": "ਪੈਲਿਕਨ",
        "image": "https://example.com/images/pelican.jpg"
    },
    {
        "animal": "Penguin",
        "gurmukhi": "ਪੇਂਗੁਇਨ",
        "image": "https://example.com/images/penguin.jpg"
    },
    {
        "animal": "Pigeon",
        "gurmukhi": "ਪਿਜਨ",
        "image": "https://example.com/images/pigeon.jpg"
    },
    {
        "animal": "Platypus",
        "gurmukhi": "ਪਲੇਟਿਪਸ",
        "image": "https://example.com/images/platypus.jpg"
    },
    {
        "animal": "Porcupine",
        "gurmukhi": "ਪੋਰਕਿਊਪਾਈਨ",
        "image": "https://example.com/images/porcupine.jpg"
    },
    {
        "animal": "Puffin",
        "gurmukhi": "ਪਫਿਨ",
        "image": "https://example.com/images/puffin.jpg"
    },
    {
        "animal": "Quail",
        "gurmukhi": "ਕੁਏਲ",
        "image": "https://example.com/images/quail.jpg"
    },
    {
        "animal": "Rabbit",
        "gurmukhi": "ਰੈਬਿਟ",
        "image": "https://example.com/images/rabbit.jpg"
    },
    {
        "animal": "Rhinoceros",
        "gurmukhi": "ਰਾਈਨੋਸੋਰਸ",
        "image": "https://example.com/images/rhinoceros.jpg"
    },
    {
        "animal": "Seal",
        "gurmukhi": "ਸੀਲ",
        "image": "https://example.com/images/seal.jpg"
    },
    {
        "animal": "Shark",
        "gurmukhi": "ਸ਼ਾਰਕ",
        "image": "https://example.com/images/shark.jpg"
    },
    {
        "animal": "Sheep",
        "gurmukhi": "ਸ਼ੀਪ",
        "image": "https://example.com/images/sheep.jpg"
    },
    {
        "animal": "Sloth",
        "gurmukhi": "ਸਲੋਥ",
        "image": "https://example.com/images/sloth.jpg"
    },
    {
        "animal": "Snake",
        "gurmukhi": "ਸਨੇਕ",
        "image": "https://example.com/images/snake.jpg"
    },
    {
        "animal": "Sparrow",
        "gurmukhi": "ਸਪੈਰੋ",
        "image": "https://example.com/images/sparrow.jpg"
    },
    {
        "animal": "Spider",
        "gurmukhi": "ਸਪਾਈਡਰ",
        "image": "https://example.com/images/spider.jpg"
    },
    {
        "animal": "Squirrel",
        "gurmukhi": "ਸਕੁਇਰਲ",
        "image": "https://example.com/images/squirrel.jpg"
    },
    {
        "animal": "Starfish",
        "gurmukhi": "ਸਟਾਰਫਿਸ਼",
        "image": "https://example.com/images/starfish.jpg"
    },
    {
        "animal": "Stork",
        "gurmukhi": "ਸਟਾਰਕ",
        "image": "https://example.com/images/stork.jpg"
    },
    {
        "animal": "Swallow",
        "gurmukhi": "ਸਵਾਲੋ",
        "image": "https://example.com/images/swallow.jpg"
    },
    {
        "animal": "Tiger",
        "gurmukhi": "ਟਾਈਗਰ",
        "image": "https://example.com/images/tiger.jpg"
    },
    {
        "animal": "Turtle",
        "gurmukhi": "ਟਰਟਲ",
        "image": "https://example.com/images/turtle.jpg"
    },
    {
        "animal": "Turkey",
        "gurmukhi": "ਟਰਕੀ",
        "image": "https://example.com/images/turkey.jpg"
    },
    {
        "animal": "Vulture",
        "gurmukhi": "ਵਲਚਰ",
        "image": "https://example.com/images/vulture.jpg"
    },
    {
        "animal": "Walrus",
        "gurmukhi": "ਵਾਲਰਸ",
        "image": "https://example.com/images/walrus.jpg"
    },
    {
        "animal": "Whale",
        "gurmukhi": "ਵੇਲ",
        "image": "https://example.com/images/whale.jpg"
    },
    {
        "animal": "Wolf",
        "gurmukhi": "ਵੋਲਫ",
        "image": "https://example.com/images/wolf.jpg"
    },
    {
        "animal": "Woodpecker",
        "gurmukhi": "ਵੁਡਪੇਕਰ",
        "image": "https://example.com/images/woodpecker.jpg"
    },
    {
        "animal": "Yak",
        "gurmukhi": "ਯਾਕ",
        "image": "https://example.com/images/yak.jpg"
    },
    {
        "animal": "Zebra",
        "gurmukhi": "ਜ਼ੀਬਰਾ",
        "image": "https://example.com/images/zebra.jpg"
    }
]
}